{
	"info": {
		"_postman_id": "8f260222-6b94-42e3-ad13-33d7cae07b87",
		"name": "TAF-DATA-STORE",
		"schema": "https://schema.getpostman.com/json/collection/v2.1.0/collection.json",
		"_exporter_id": "24372547"
	},
	"item": [
		{
			"name": "TAFDatastore",
			"item": [
				{
					"name": "GetUsers",
					"request": {
						"method": "GET",
						"header": [],
						"url": {
							"raw": "http://localhost:8081/users",
							"protocol": "http",
							"host": [
								"localhost"
							],
							"port": "8081",
							"path": [
								"users"
							]
						}
					},
					"response": []
				},
				{
					"name": "GetFlights",
					"request": {
						"method": "GET",
						"header": [],
						"url": {
							"raw": "http://localhost:8081/users",
							"protocol": "http",
							"host": [
								"localhost"
							],
							"port": "8081",
							"path": [
								"users"
							]
						}
					},
					"response": []
				},
				{
					"name": "GetBookings",
					"request": {
						"method": "GET",
						"header": [],
						"url": {
							"raw": "http://localhost:8081/users",
							"protocol": "http",
							"host": [
								"localhost"
							],
							"port": "8081",
							"path": [
								"users"
							]
						}
					},
					"response": []
				}
			]
		}
	]
}